Exia/Cerebro.py
Exia/__init__.py
Exia/_tricks.py
Exia/_version_params.py
Exia/influx_conn.py
Exia/api/__init__.py
Exia/api/data_api.py
Exia_Zzx-0.1.0a0.dist-info/LICENSE
Exia_Zzx-0.1.0a0.dist-info/METADATA
Exia_Zzx-0.1.0a0.dist-info/WHEEL
Exia_Zzx-0.1.0a0.dist-info/top_level.txt
Exia_Zzx-0.1.0a0.dist-info/RECORD
